cli.py
decidra/__init__.py
decidra/monitor_app.py
decidra/post_install.py
decidra/py.typed
decidra/run_tests.py
decidra/api/__init__.py
decidra/api/futu.py
decidra/api/futu_client.py
decidra/api/futu_factory.py
decidra/api/futu_quote.py
decidra/api/futu_trade.py
decidra/base/__init__.py
decidra/base/ai.py
decidra/base/futu_class.py
decidra/base/futu_modue.py
decidra/base/monitor.py
decidra/base/order.py
decidra/base/trading.py
decidra/examples/advanced_kline_chart_example.py
decidra/examples/auto_dialog_example.py
decidra/examples/claude_ai_example.py
decidra/examples/confirm_dialog_example.py
decidra/examples/futu_trade_example.py
decidra/examples/info_panel_demo.py
decidra/examples/kline_chart_example.py
decidra/examples/monitor_interface_example.py
decidra/examples/order_debug_test.py
decidra/examples/order_dialog_example.py
decidra/examples/quick_test.py
decidra/examples/simple_autocomplete_test.py
decidra/examples/simple_claude_test.py
decidra/examples/tab_example.py
decidra/examples/watch.py
decidra/examples/window_dialog_example.py
decidra/examples/_funcat-stocks/choose_stock.py
decidra/examples/_funcat-stocks/choose_stock_akshare.py
decidra/examples/_funcat-stocks/choose_stock_hk.py
decidra/examples/_funcat-stocks/choose_stock_us.py
decidra/examples/_funcat-stocks/stock_buy_signal_2months.py
decidra/examples/_funcat-stocks/stock_sift.py
decidra/examples/_funcat-stocks/validation.py
decidra/modules/__init__.py
decidra/modules/futu_market.py
decidra/modules/futu_trade.py
decidra/modules/jsonlite_data.py
decidra/modules/supabase.py
decidra/modules/yahoo_data.py
decidra/modules/yahoo_stock.py
decidra/modules/ai/__init__.py
decidra/modules/ai/claude_ai_client.py
decidra/monitor/__init__.py
decidra/monitor/app_core.py
decidra/monitor/monitor_layout.py
decidra/monitor/analysis/__init__.py
decidra/monitor/analysis/ai_analysis_manager.py
decidra/monitor/analysis/analysis_data_manager.py
decidra/monitor/analysis/chart_manager.py
decidra/monitor/main/__init__.py
decidra-1.0.2.dist-info/LICENSE
decidra-1.0.2.dist-info/METADATA
decidra-1.0.2.dist-info/WHEEL
decidra-1.0.2.dist-info/entry_points.txt
decidra-1.0.2.dist-info/top_level.txt
decidra-1.0.2.dist-info/RECORD
