Metadata-Version: 2.1
Name: decidra
Version: 1.0.2
Summary: Intelligent Trading Decision System - Python Stock Trading Analysis Platform Based on Futu OpenAPI
Author-email: rtx3 <r@rtx3.com>
Maintainer-email: rtx3 <r@rtx3.com>
License: MIT License
Project-URL: Homepage, https://github.com/rtxIII/decidra
Project-URL: Documentation, https://decidra.readthedocs.io/
Project-URL: Repository, https://github.com/rtxIII/decidra.git
Project-URL: Bug Tracker, https://github.com/rtxIII/decidra/issues
Project-URL: Changelog, https://github.com/rtxIII/decidra/blob/main/CHANGELOG.md
Keywords: trading,stock,futu,api,finance,analysis,textual,terminal
Classifier: Development Status :: 4 - Beta
Classifier: Intended Audience :: Financial and Insurance Industry
Classifier: Intended Audience :: Developers
Classifier: Operating System :: OS Independent
Classifier: Programming Language :: Python :: 3
Classifier: Programming Language :: Python :: 3.8
Classifier: Programming Language :: Python :: 3.9
Classifier: Programming Language :: Python :: 3.10
Classifier: Programming Language :: Python :: 3.11
Classifier: Programming Language :: Python :: 3.12
Classifier: Topic :: Office/Business :: Financial
Classifier: Topic :: Software Development :: Libraries :: Python Modules
Classifier: Topic :: System :: Monitoring
Classifier: Topic :: Terminals
Requires-Python: >=3.8
License-File: LICENSE
Requires-Dist: setuptools
Requires-Dist: wheel
Requires-Dist: numpy==1.26.4
Requires-Dist: six
Requires-Dist: backports.functools-lru-cache
Requires-Dist: pandas==1.5.3
Requires-Dist: lxml
Requires-Dist: requests
Requires-Dist: cached-property
Requires-Dist: tqdm
Requires-Dist: python-dateutil
Requires-Dist: pytz
Requires-Dist: idna
Requires-Dist: certifi
Requires-Dist: soupsieve
Requires-Dist: websocket-client
Requires-Dist: charset-normalizer
Requires-Dist: tushare
Requires-Dist: akshare
Requires-Dist: yfinance==0.2.64
Requires-Dist: futu-api==9.3.5308
Requires-Dist: funcat3==1.1.8
Requires-Dist: jsonlite
Requires-Dist: humanize
Requires-Dist: candlestick-chart==3.1.0
Requires-Dist: psutil
Requires-Dist: pyyaml
Requires-Dist: pyarrow
Requires-Dist: scikit-learn==1.7.0
Requires-Dist: click==8.1.7
Requires-Dist: rich==13.9.4
Requires-Dist: rich-interactive==0.6.0
Requires-Dist: colorama
Requires-Dist: textual
Requires-Dist: textual-window==0.5.2
Requires-Dist: textual-autocomplete==4.0.4
Requires-Dist: textual-slidecontainer
Requires-Dist: textual-plotext==1.0.1
Requires-Dist: claude-code-sdk
Provides-Extra: dev
Requires-Dist: pylint; extra == "dev"
Requires-Dist: pytest>=6.0; extra == "dev"
Requires-Dist: pytest-cov; extra == "dev"
Requires-Dist: pytest-asyncio; extra == "dev"
Requires-Dist: black; extra == "dev"
Requires-Dist: isort; extra == "dev"
Requires-Dist: mypy; extra == "dev"
Requires-Dist: pre-commit; extra == "dev"
Provides-Extra: docs
Requires-Dist: mkdocs; extra == "docs"
Requires-Dist: mkdocs-material; extra == "docs"
Requires-Dist: mkdocstrings[python]; extra == "docs"
Provides-Extra: test
Requires-Dist: pytest>=6.0; extra == "test"
Requires-Dist: pytest-cov; extra == "test"
Requires-Dist: pytest-asyncio; extra == "test"
Requires-Dist: pytest-mock; extra == "test"
